{
    "name": "SimPARTIXOutput",
    "version": "0.0.1",
    "namespace": "http://onto-ns.com/meta",
    "meta": "http://onto-ns.com/meta/0.3/EntitySchema",
    "description": "Output of a SimPARTIX melt pool simulation (MarketPlace UC1).",
    "dimensions": [
      {
        "name": "X",
        "description": "Number of cells in x direction."
      },
      {
        "name": "Z",
        "description": "Number of cells in z direction."
      }
    ],
    "properties": [
      {
        "_comment": "needs to be linked to -> ThermodynamicTemperature, http://emmo.info/emmo#EMMO_affe07e4_e9bc_4852_86c6_69e26182a17f",
        "name": "temperature",
        "type": "float",
        "unit": "Kelvin",
        "dims": ["X", "Z"],
        "description": "List of temperature cells."
      },
      {
        "_comment": "probably needs a new entity, for now we can use Index, http://emmo.info/emmo#EMMO_0cd58641_824c_4851_907f_f4c3be76630c",
        "name": "group",
        "type": "int",
        "dims": ["X", "Z"],
        "description": "List of group (i.e. grain) cells."
      },
      {
        "_comment": "needs to be linked to -> StateOfMatter, http://emmo.info/emmo#EMMO_b9695e87_8261_412e_83cd_a86459426a28",
        "name": "state_of_matter",
        "type": "int",
        "dims": ["X", "Z"],
        "description": "List of state of matter (i.e. phase) cells."
      }
    ]
}
